flake8_max_function_length/__init__.py
flake8_max_function_length/plugin.py
flake8_max_function_length-0.10.0.dist-info/entry_points.txt
flake8_max_function_length-0.10.0.dist-info/licenses/LICENSE
flake8_max_function_length-0.10.0.dist-info/WHEEL
flake8_max_function_length-0.10.0.dist-info/METADATA
flake8_max_function_length-0.10.0.dist-info/RECORD
