Metadata-Version: 2.4
Name: flake8-max-function-length
Version: 0.10.0
Summary: A configurable flake8 plugin to enforce a maximum function/method length.
Keywords: flake8,flake8 plugin,maximum function length
Author: Ghazi Abbassi
Requires-Python: >=3.8
Classifier: Intended Audience :: Developers
Classifier: License :: OSI Approved :: MIT License
Classifier: Programming Language :: Python :: 3
Classifier: Programming Language :: Python :: 3.8
Classifier: Programming Language :: Python :: 3.9
Classifier: Programming Language :: Python :: 3.10
Classifier: Programming Language :: Python :: 3.11
Classifier: Programming Language :: Python :: 3.12
Classifier: Programming Language :: Python :: 3.13
Classifier: Programming Language :: Python :: 3.14
License-File: LICENSE
Requires-Dist: flake8
Requires-Dist: pre-commit ; extra == "dev"
Requires-Dist: flit ; extra == "release"
Requires-Dist: keyring ; extra == "release"
Requires-Dist: tbump ; extra == "release"
Requires-Dist: pytest ; extra == "test"
Requires-Dist: pre-commit ; extra == "test"
Project-URL: Changelog, https://github.com/ghazi-git/flake8-max-function-length/releases
Project-URL: Code, https://github.com/ghazi-git/flake8-max-function-length
Project-URL: Issues, https://github.com/ghazi-git/flake8-max-function-length/issues
Provides-Extra: dev
Provides-Extra: release
Provides-Extra: test
